s_proc_v1/rtl/prototypes/pc/pc.v
module pc(
	  clk,
	  rst,
	  c_e,
	  adrs_in,
	  adrs_out,
	  en_pc
	  );
   input wire clk;
   input wire rst;
   input wire c_e;
   input wire [7:0] adrs_in;
   input wire 	    en_pc;
   
   output  wire [7:0] adrs_out;
   reg [7:0] 	    temp_adrs;
   
   always @(posedge clk or negedge rst)
     begin
	if(c_e & en_pc === 1'b0)
	  begin
	  end
	else if(rst === 1'b0)
	  begin
	     temp_adrs <= 8'b00000000;
	  end
	else
	  begin
	     temp_adrs <= adrs_in;
	  end
     end // always @ (posedge clk or negedge rst or negedge c_e)
   assign adrs_out = temp_adrs;
   
   
endmodule

s_proc_v1/rtl/prototypes/pc/pc_tb.v
module pc_tb;
   reg tstclk;
   reg tstrst;
   reg tstc_e;
   reg [7:0] tstadrs_in;
   reg 	     tsten_pc ;
   wire [7:0] tstadrs_out;

   pc dut(
	  .clk(tstclk),
	  .rst(tstrst),
	  .c_e(tstc_e),
	  .adrs_in(tstadrs_in),
	  .adrs_out(tstadrs_out),
	  .en_pc(tsten_pc)
	  );
   always
     begin
	tstclk <= 0 ;
	#5;
	tstclk <= 1 ;
	#5;
     end
   
   initial
     begin
	$dumpvars;
	
	tstrst <= 1'b0;
	tstc_e <= 1'b1;
	tsten_pc <= 1'b1;
	
	
	
	@(posedge tstclk)
	  begin
	     tstrst <= 1'b1;
	     tstadrs_in <= 8'b00000001;
	     
	  end
        @(posedge tstclk)
	  begin
	     tstadrs_in <= 8'b00000010;
	     
	     
	  end
	@(posedge tstclk)
	  tstadrs_in <= 8'b00000011;
	@(posedge tstclk)
	  
	  begin
	     tstadrs_in <= 8'b00000100;
	     tstc_e <= 1'b0;
	     
	  end
	@(posedge tstclk)
	  tstc_e <= 1'b1;
	
	
	@(posedge tstclk)
	  tstadrs_in <= 8'b00000101;
	
	#50;
	
	$finish;
     end
   
   
   
    
endmodule

s_proc_v1/rtl/prototypes/pc/dump.vcd
$date
	Sun Nov 20 15:13:26 2022
$end
$version
	Icarus Verilog
$end
$timescale
	1s
$end
$scope module pc_tb $end
$var wire 8 ! tstadrs_out [7:0] $end
$var reg 8 " tstadrs_in [7:0] $end
$var reg 1 # tstc_e $end
$var reg 1 $ tstclk $end
$var reg 1 % tsten_pc $end
$var reg 1 & tstrst $end
$scope module dut $end
$var wire 8 ' adrs_in [7:0] $end
$var wire 8 ( adrs_out [7:0] $end
$var wire 1 # c_e $end
$var wire 1 $ clk $end
$var wire 1 % en_pc $end
$var wire 1 & rst $end
$var reg 8 ) temp_adrs [7:0] $end
$upscope $end
$upscope $end
$enddefinitions $end
#0
$dumpvars
b0 )
b0 (
bx '
0&
1%
0$
1#
bx "
b0 !
$end
#5
b1 "
b1 '
1&
1$
#10
0$
#15
b1 !
b1 (
b1 )
b10 "
b10 '
1$
#20
0$
#25
b10 !
b10 (
b10 )
b11 "
b11 '
1$
#30
0$
#35
b11 !
b11 (
b11 )
0#
b100 "
b100 '
1$
#40
0$
#45
b100 !
b100 (
b100 )
1#
1$
#50
0$
#55
b101 "
b101 '
1$
#60
0$
#65
b101 !
b101 (
b101 )
1$
