s_proc_v1/rtl/top level/ir.v
//////////////////////////////////////////////////////////////////////
//
// Author : Omkar Girish Kamath
// Instruction Register Prototype
// Data : 20 / 11 / 22
//
//////////////////////////////////////////////////////////////////////

module ir(
          clk,
          rst,
          d_in,
          d_out,
	  en_ir
          );
   
   input wire rst;
   input wire clk;
   input wire en_ir;
   input wire [15:0] d_in;
   
   output reg [15:0] d_out;
   
   always @(posedge clk or negedge rst)
     begin
	if(rst === 1'b0)
	  begin
	     d_out <= 'h0;
	  end
	else
	  if(en_ir === 1'b1)
	    begin
	       d_out <= d_in;
	    end
     end
   
endmodule

s_proc_v1/rtl/prototypes/ir/ir_tb.v
module ir_tb;
   reg tstclk;
   reg tstrst;
   reg [15:0] tstd_in;
   reg 	      tsten_ir ;
   
   wire [15:0] tstd_out;

   ir dut(
	  .clk(tstclk),
	  .rst(tstrst),
	  .d_in(tstd_in),
	  .d_out(tstd_out),
	  .en_ir(tsten_ir)
	  );
   always
     begin
	tstclk <= 1;
	#5;
	tstclk <= 0;
	#5;
     end
   initial
     begin
	$dumpvars;
	tstd_in <= 0000000010110001;
	tsten_ir <= 1'b1;
	tstrst <= 1'b0;
	
	
	
        @(posedge tstclk)
	  begin
	     tstd_in <= 0100001110110001;
	     
	     
	  end
	
       
	@(posedge tstclk)
	  begin
	     tstd_in <= 0001000100110001;
	     tstrst <= 1'b1;
	     
	  end
	
       
	@(posedge tstclk)
	  begin
	     
	     tstd_in <= 0000000010110001;
	  end
	
       
	@(posedge tstclk)
	  begin
	     tstd_in <= 1000000010110001;
	     tsten_ir <= 1'b0;
	  end
       
	@(posedge tstclk)
	  begin
	     tstd_in <= 1100110010110001;
	  end
	@(posedge tstclk)
	  begin
	     tstd_in <= 0001000111110001;
	     tsten_ir <= 1'b1;
	     
	  end
	@(posedge tstclk)
	  begin
	     tstd_in <= 0001000100110001;
	    	     
	  end
	#100;
	
	$finish;
     end
endmodule // ir_tb

s_proc_v1/rtl/prototypes/ir/dump.vcd
$date
	Wed Nov 23 03:43:18 2022
$end
$version
	Icarus Verilog
$end
$timescale
	1s
$end
$scope module ir_tb $end
$var wire 16 ! tstd_out [15:0] $end
$var reg 1 " tstclk $end
$var reg 16 # tstd_in [15:0] $end
$var reg 1 $ tsten_ir $end
$var reg 1 % tstrst $end
$scope module dut $end
$var wire 1 " clk $end
$var wire 16 & d_in [15:0] $end
$var wire 1 $ en_ir $end
$var wire 1 % rst $end
$var reg 16 ' d_out [15:0] $end
$upscope $end
$upscope $end
$enddefinitions $end
#0
$dumpvars
b0 '
b10111100110001 &
0%
1$
b10111100110001 #
1"
b0 !
$end
#5
0"
#10
1%
b1001111010110001 #
b1001111010110001 &
1"
#15
0"
#20
b1001111010110001 !
b1001111010110001 '
b100010000110001 #
b100010000110001 &
1"
#25
0"
#30
b100010000110001 !
b100010000110001 '
0$
b1100010000110001 #
b1100010000110001 &
1"
#35
0"
#40
b1101000000110001 #
b1101000000110001 &
1"
#45
0"
#50
1$
b111011101110001 #
b111011101110001 &
1"
#55
0"
#60
b111011101110001 !
b111011101110001 '
b1001111010110001 #
b1001111010110001 &
1"
#65
0"
#70
b1001111010110001 !
b1001111010110001 '
1"
