s_proc_v1/rtl/prototypes/seq_gen.v
module seq_gen(
	       clk,
    	       clr,
	       f,
	       d,
	       e,
	       i
	       );
   input clk;
   
   input clr;
   output wire f;
   output wire d;
   output wire e;
   output wire i;
   
   
   reg [3:0] state;
   always @(posedge clk or negedge clr)
     begin
	
	if(clr === 1'b0)
	  begin
	     state <= 4'b0000;
	     
	  end
	else
	  begin
	     case(state)
	       4'b0000:
		 begin
		    state <= 4'b1000;
		 end
	       4'b1000:
		 begin
		    state <= 4'b0100;
		 end
	       4'b0100:
		 begin
		    state <= 4'b0010;
		 end
	       4'b0010:
		 begin
		    state <= 4'b0001;
		 end
	       4'b0001:
		 begin
		    state <= 4'b1000;
		 end
	       default:	// 
		 begin
		    state <= 4'b0000;
		 end
	     endcase // case (state)
	     
	  end
     end // always @ (posedge clk or negedge clr)
   assign f = state[3];
   assign d = state[2];
   assign e = state[1];
   assign i = state[0];
   
endmodule // seq_gen

s_proc_v1/rtl/prototypes/decoder/seq_gen_tb.v
module seq_gen_tb;
   reg tstclk;
   
   reg 	     tstclr;
   wire      tstf;
   wire      tstd;
   wire      tste;
   wire      tsti;
   

   seq_gen dut(
	       .clk(tstclk),
	       .clr(tstclr),
	       .f(tstf),
	       .d(tstd),
	       .e(tste),
	       .i(tsti)
	       );
   
   always
     begin
      #5   tstclk <= 0;
      #5   tstclk <= 1;
     end
   initial
     begin
	$dumpvars;
	#20;
	@(posedge tstclk)
	tstclr <= 0;
	#20;
	@(posedge tstclk)
	tstclr <= 1;
	#100;
	
		  
	$finish;
	
     end
endmodule

s_proc_v1/rtl/prototypes/dump.vcd
$date
	Fri Nov 25 01:10:45 2022
$end
$version
	Icarus Verilog
$end
$timescale
	1s
$end
$scope module seq_gen_tb $end
$var wire 1 ! tsti $end
$var wire 1 " tstf $end
$var wire 1 # tste $end
$var wire 1 $ tstd $end
$var reg 1 % tstclk $end
$var reg 1 & tstclr $end
$scope module dut $end
$var wire 1 % clk $end
$var wire 1 & clr $end
$var wire 1 ! i $end
$var wire 1 " f $end
$var wire 1 # e $end
$var wire 1 $ d $end
$var reg 4 ' state [3:0] $end
$upscope $end
$upscope $end
$enddefinitions $end
#0
$dumpvars
bx '
x&
x%
x$
x#
x"
x!
$end
#5
0%
#10
0"
0$
0#
0!
b0 '
1%
#15
0%
#20
0"
b0 '
0&
1%
#25
0%
#30
1%
#35
0%
#40
1&
1%
#45
0%
#50
1"
b1000 '
1%
#55
0%
#60
0"
1$
b100 '
1%
#65
0%
#70
0$
1#
b10 '
1%
#75
0%
#80
0#
1!
b1 '
1%
#85
0%
#90
1"
0!
b1000 '
1%
#95
0%
#100
0"
1$
b100 '
1%
#105
0%
#110
0$
1#
b10 '
1%
#115
0%
#120
0#
1!
b1 '
1%
#125
0%
#130
1"
0!
b1000 '
1%
#135
0%
#140
0"
1$
b100 '
1%
